testrailrobot/__init__.py
testrailrobot/api.py
testrailrobot/core.py
testrailrobot/errors.py
testrailrobot-0.9.1.dist-info/DESCRIPTION.rst
testrailrobot-0.9.1.dist-info/METADATA
testrailrobot-0.9.1.dist-info/RECORD
testrailrobot-0.9.1.dist-info/WHEEL
testrailrobot-0.9.1.dist-info/metadata.json
testrailrobot-0.9.1.dist-info/top_level.txt
