Metadata-Version: 2.0
Name: testrailrobot
Version: 0.9.1
Summary: Package for uploading test results from Robot Framework to TestRail.
Home-page: https://github.com/taneltorn/testrailrobot
Author: Tanel Torn
Author-email: tanel.torn@gmail.com
License: MIT
